dict2dict/__init__.py
dict2dict/clean.py
dict2dict/merge.py
dict2dict/transform.py
dict2dict-0.4.1.dist-info/LICENSE
dict2dict-0.4.1.dist-info/METADATA
dict2dict-0.4.1.dist-info/WHEEL
dict2dict-0.4.1.dist-info/top_level.txt
dict2dict-0.4.1.dist-info/RECORD
