Metadata-Version: 2.1
Name: dict2dict
Version: 0.4.1
Summary: Opinionated dictionary utilities for Python.
Author-email: lykmapipo <lallyelias87@gmail.com>
Maintainer-email: lykmapipo <lallyelias87@gmail.com>
License: MIT
Project-URL: Homepage, https://github.com/lykmapipo/dict2dict
Project-URL: Documentation, https://github.com/lykmapipo/dict2dict
Project-URL: Changelog, https://github.com/lykmapipo/dict2dict/blob/main/CHANGELOG.md
Project-URL: Repository, https://github.com/lykmapipo/dict2dict
Project-URL: Issues, https://github.com/lykmapipo/dict2dict/issues
Keywords: lykmapipo,dictionary,dict,utilities,utils,helpers,transform,merge,omit,remove,normalize
Classifier: Development Status :: 4 - Beta
Classifier: Environment :: Console
Classifier: Intended Audience :: Developers
Classifier: License :: OSI Approved :: MIT License
Classifier: Natural Language :: English
Classifier: Operating System :: OS Independent
Classifier: Programming Language :: Python
Classifier: Programming Language :: Python :: 3
Classifier: Programming Language :: Python :: 3 :: Only
Classifier: Programming Language :: Python :: 3.8
Classifier: Programming Language :: Python :: 3.9
Classifier: Programming Language :: Python :: 3.10
Classifier: Programming Language :: Python :: 3.11
Classifier: Programming Language :: Python :: 3.12
Classifier: Programming Language :: Python :: 3.13
Classifier: Topic :: Software Development
Classifier: Topic :: Software Development :: Libraries
Classifier: Topic :: Software Development :: Libraries :: Python Modules
Classifier: Topic :: Utilities
Classifier: Typing :: Typed
Requires-Python: >=3.8
License-File: LICENSE
Provides-Extra: dev
Requires-Dist: black >=24.4.2 ; extra == 'dev'
Requires-Dist: build >=1.2.1 ; extra == 'dev'
Requires-Dist: codespell[toml] >=2.3.0 ; extra == 'dev'
Requires-Dist: commitizen >=3.27.0 ; extra == 'dev'
Requires-Dist: coverage[toml] >=7.5.4 ; extra == 'dev'
Requires-Dist: isort >=5.13.2 ; extra == 'dev'
Requires-Dist: mypy >=1.10.1 ; extra == 'dev'
Requires-Dist: pip-audit >=2.7.3 ; extra == 'dev'
Requires-Dist: pre-commit >=3.5.0 ; extra == 'dev'
Requires-Dist: pytest >=8.2.2 ; extra == 'dev'
Requires-Dist: pytest-cov >=5.0.0 ; extra == 'dev'
Requires-Dist: pytest-xdist >=3.6.1 ; extra == 'dev'
Requires-Dist: pydocstyle >=6.3.0 ; extra == 'dev'
Requires-Dist: ruff >=0.5.1 ; extra == 'dev'
Requires-Dist: setuptools >=70.3.0 ; extra == 'dev'
Requires-Dist: twine >=5.1.1 ; extra == 'dev'
